mcp_genelab/__init__.py
mcp_genelab/server.py
mcp_genelab/server_mod1.py
mcp_genelab/server_mod2.py
mcp_genelab/server_mod3.py
mcp_genelab-0.4.0.dist-info/METADATA
mcp_genelab-0.4.0.dist-info/WHEEL
mcp_genelab-0.4.0.dist-info/entry_points.txt
mcp_genelab-0.4.0.dist-info/licenses/LICENSE
mcp_genelab-0.4.0.dist-info/RECORD
