Metadata-Version: 2.4
Name: mcp-genelab
Version: 0.4.0
Summary: MCP server for querying Neo4j Knowledge Graphs with custom tools for quering GeneLab
Project-URL: Homepage, https://github.com/sbl-sdsc/mcp-genelab
Project-URL: Repository, https://github.com/sbl-sdsc/mcp-genelab
Project-URL: Issues, https://github.com/sbl-sdsc/mcp-genelab/issues
Author-email: Peter W Rose <pwrose.ucsd@gmail.com>
License: BSD-3-Clause
License-File: LICENSE
Keywords: GeneLab,NASA,OSDR,mcp,proto-okn
Classifier: Development Status :: 4 - Beta
Classifier: Intended Audience :: Developers
Classifier: License :: OSI Approved :: BSD License
Classifier: Programming Language :: Python :: 3.10
Classifier: Programming Language :: Python :: 3.11
Classifier: Programming Language :: Python :: 3.12
Requires-Python: >=3.10
Requires-Dist: adjusttext
Requires-Dist: matplotlib
Requires-Dist: matplotlib-venn
Requires-Dist: mcp>=1.6.0
Requires-Dist: neo4j>=5.26.0
Requires-Dist: numpy
Requires-Dist: pydantic>=2.10.1
